MANIFEST.in
README.md
license.txt
setup.py
PyJSBSim.egg-info/PKG-INFO
PyJSBSim.egg-info/SOURCES.txt
PyJSBSim.egg-info/dependency_links.txt
PyJSBSim.egg-info/requires.txt
PyJSBSim.egg-info/top_level.txt
cython/fgfdmexec.cpp
cython/fgfdmexec.pyx
examples/737_bada_gen.py
examples/devpath.py
examples/plot.py
examples/pyjsbsim-737-demo.txt
examples/scaneagle_bada_gen.py
pyjsbsim/__init__.py
pyjsbsim/bada.py
pyjsbsim/utils.py
pyjsbsim/files/bada_ptf.template
scripts/bada_print.py
scripts/devpath.py
test/__init__.py
test/bada.py
test/cython.py
test/devpath.py