Metadata-Version: 1.1
Name: PyJSBSim
Version: 0.5.6
Summary: A python interface for JSBSim using Cython.
Home-page: https://github.com/arktools/pyjsbsim
Author: James Goppert
Author-email: james.goppert@gmail.com
License: GPLv3
Platform: UNKNOWN
Classifier: Development Status :: 4 - Beta
Classifier: Environment :: Console
Classifier: Intended Audience :: Science/Research
Classifier: License :: OSI Approved :: GNU General Public License v3 (GPLv3)
Classifier: Operating System :: OS Independent
Classifier: Programming Language :: Python :: 2.7
Classifier: Topic :: Scientific/Engineering
Classifier: Topic :: Text Processing :: General
